Metadata-Version: 2.1
Name: ucsc-genomic-api
Version: 1.0.2
Summary: access and query the UCSC database with an elegant and human readable Api
Home-page: https://github.com/Eyadhamza/UCSC-Genomic-REST-Api-Wrapper
Author: Eyad Hamza
Author-email: eyadhamza0@outlook.com
License: MIT
Download-URL: https://github.com/Eyadhamza/UCSC-Genomic-REST-Api-Wrapper/releases/tag/1.0.0
Keywords: python,genomic,bioinformatics,bio,genomes,ucsc
Platform: UNKNOWN
Classifier: Development Status :: 5 - Production/Stable
Classifier: Intended Audience :: Developers
Classifier: Topic :: Software Development :: Build Tools
Classifier: Programming Language :: Python :: 3.6
Requires-Dist: requests
